evaluator_blog/__init__.py
evaluator_blog/evaluator.py
evaluator_blog/metrics/__init__.py
evaluator_blog/metrics/bleu.py
evaluator_blog/metrics/rouge.py
evaluator_blog/tests/test_rouge.py
evaluator_blog-0.1.0.dist-info/LICENSE
evaluator_blog-0.1.0.dist-info/METADATA
evaluator_blog-0.1.0.dist-info/WHEEL
evaluator_blog-0.1.0.dist-info/RECORD
