Metadata-Version: 2.1
Name: evaluator-blog
Version: 0.1.0
Summary: 
Author: Sriniketh J
Author-email: srinikethcr7@gmail.com
Requires-Python: >=3.12,<4.0
Classifier: Programming Language :: Python :: 3
Classifier: Programming Language :: Python :: 3.12
Requires-Dist: nltk (>=3.8.1,<4.0.0)
Requires-Dist: pytest (>=8.2.2,<9.0.0)
Requires-Dist: rouge-score (>=0.1.2,<0.2.0)
